{
  "generated_at": "2025-12-26T16:16:03.133737+08:00",
  "total_titles_processed": 1262,
  "failed_sources": [],
  "trends": [
    {
      "keyword_group": "人工智能",
      "match_count": 9,
      "titles": [
        {
          "title": "国家发改委：国家创业投资引导基金将对集成电路、人工智能、航空航天、低空经济等领域的早期项目和企业加大投资力度",
          "url": "https://www.cls.cn/detail/2240698",
          "source": "财联社热门",
          "ranks": [
            4,
            3,
            2,
            1
          ],
          "is_new": false,
          "appearance_count": 8,
          "time_info": "[11时53分 ~ 16时16分]"
        },
        {
          "title": "据日经新闻：富士通加入由软银牵头的下一代人工智能内存项目。",
          "url": "https://flash.jin10.com/detail/20251226040528613800",
          "source": "金十数据",
          "ranks": [
            4,
            6,
            9
          ],
          "is_new": false,
          "appearance_count": 3,
          "time_info": "[05时10分 ~ 07时11分]"
        },
        {
          "title": "报道：鸿海向日本政府寻求补贴 以在当地生产人工智能服务器",
          "url": "https://wallstreetcn.com/livenews/3027044",
          "source": "华尔街见闻-快讯",
          "ranks": [
            2,
            16
          ],
          "is_new": false,
          "appearance_count": 2,
          "time_info": "[13时14分 ~ 14时18分]"
        },
        {
          "title": "朱光耀：人工智能发展需在伦理规范与治理规则方面形成共识",
          "url": "https://wallstreetcn.com/livenews/3027016",
          "source": "华尔街见闻-快讯",
          "ranks": [
            6,
            12,
            19
          ],
          "is_new": false,
          "appearance_count": 3,
          "time_info": "[11时53分 ~ 13时14分]"
        },
        {
          "title": "工业和信息化部：今年人工智能核心产业规模超万亿元",
          "url": "https://wallstreetcn.com/livenews/3027068",
          "source": "华尔街见闻-快讯",
          "ranks": [
            7,
            24
          ],
          "is_new": false,
          "appearance_count": 2,
          "time_info": "[14时18分 ~ 15时14分]"
        },
        {
          "title": "金十数据整理：每日人工智能动态汇总（2025-12-26）",
          "url": "https://flash.jin10.com/detail/20251226114833609800",
          "source": "金十数据",
          "ranks": [
            9,
            12
          ],
          "is_new": false,
          "appearance_count": 2,
          "time_info": "[12时28分 ~ 13时14分]"
        },
        {
          "title": "日本拟在预算中就对芯片和人工智能的支持增加三倍",
          "url": "https://flash.jin10.com/detail/20251226112803480800",
          "source": "金十数据",
          "ranks": [
            19,
            22
          ],
          "is_new": false,
          "appearance_count": 2,
          "time_info": "[12时28分 ~ 13时14分]"
        },
        {
          "title": "英媒：人工智能热潮料正使美国科技界富豪的净资产增加5000亿美元",
          "url": "https://flash.jin10.com/detail/20251226131433811800",
          "source": "金十数据",
          "ranks": [
            8
          ],
          "is_new": false,
          "appearance_count": 1,
          "time_info": "14时18分"
        },
        {
          "title": "今年，美国科技亿万富翁们的总净资产增加了超过5500亿美元，这得益于投资者对领先人工智能公司的狂热追捧。",
          "url": "https://flash.jin10.com/detail/20251226130758495800",
          "source": "金十数据",
          "ranks": [
            9
          ],
          "is_new": false,
          "appearance_count": 1,
          "time_info": "14时18分"
        }
      ]
    }
  ],
  "report_image_url": "https://joyce677.github.io/TrendRadar/img/news.jpg"
}