{
  "generated_at": "2026-05-25T00:49:49.212637+08:00",
  "total_titles_processed": 314,
  "failed_sources": [],
  "trends": [
    {
      "keyword_group": "人工智能",
      "match_count": 1,
      "titles": [
        {
          "title": "印度外交部长苏杰生：与来访的美国国务卿卢比奥讨论了关键矿物、人工智能（AI）、核、以及其他问题。",
          "url": "https://wallstreetcn.com/livenews/3108500",
          "source": "华尔街见闻-快讯",
          "ranks": [
            26
          ],
          "is_new": false,
          "appearance_count": 1,
          "time_info": "00时49分"
        }
      ]
    }
  ],
  "report_image_url": "https://joyce677.github.io/TrendRadar/img/news.jpg"
}